disposable_emails/__init__.py
disposable_emails/contrib/__init__.py
disposable_emails/contrib/django/__init__.py
disposable_emails/data/domains.txt
tests/__init__.py
disposable_emails-1.0.1.dist-info/LICENSE
disposable_emails-1.0.1.dist-info/METADATA
disposable_emails-1.0.1.dist-info/WHEEL
disposable_emails-1.0.1.dist-info/top_level.txt
disposable_emails-1.0.1.dist-info/RECORD
