Metadata-Version: 2.1
Name: disposable-emails
Version: 1.0.1
Summary: Weed out disposable email providers with ease
Home-page: https://github.com/maxmalysh/disposable-emails
Author: Max Malysh
Author-email: github@maxmalysh.com
License: MIT
Platform: UNKNOWN
Classifier: Programming Language :: Python :: 3
Classifier: License :: OSI Approved :: MIT License
Classifier: Operating System :: OS Independent
Classifier: Framework :: Django
Classifier: Topic :: Communications :: Email
